upm/__init__.py
upm/__main__.py
upm/build.py
upm/changelog.py
upm/config.py
upm/config.upm
upm/gitignore.upm
upm/install_vs.py
upm/install_vscode.py
upm/install_xcode.py
upm/launch.upm
upm/query.py
upm/requirements.txt
upm/setup.py
upm/tasks.upm
unreal_project_manager-0.1.4.dist-info/LICENSE.md
unreal_project_manager-0.1.4.dist-info/METADATA
unreal_project_manager-0.1.4.dist-info/WHEEL
unreal_project_manager-0.1.4.dist-info/entry_points.txt
unreal_project_manager-0.1.4.dist-info/top_level.txt
unreal_project_manager-0.1.4.dist-info/RECORD
