Metadata-Version: 2.1
Name: unreal-project-manager
Version: 0.1.4
Summary: A lightweight Python module for managing Unreal projects across space, time, and platforms.
Home-page: https://github.com/crashtestbrandt/unrealprojectmanager
Author: Brandt Frazier
Author-email: brandt@frazimuth.me
Requires-Python: >=3.10
License-File: LICENSE.md
Requires-Dist: python-dotenv
